plaid_python_adapter/__init__.py
plaid_python_adapter/exceptions.py
plaid_python_adapter/plaid_adapter.py
plaid_python_adapter-0.2.dist-info/LICENSE
plaid_python_adapter-0.2.dist-info/METADATA
plaid_python_adapter-0.2.dist-info/WHEEL
plaid_python_adapter-0.2.dist-info/top_level.txt
plaid_python_adapter-0.2.dist-info/RECORD
