Metadata-Version: 2.1
Name: plaid-python-adapter
Version: 0.2
Summary: Python library adapter for accessing Plaid APIs
Home-page: https://github.com/Lenders-Cooperative/plaid-python-adapter
Author: Tejas Bhandari
License: UNKNOWN
Platform: UNKNOWN
Classifier: Programming Language :: Python :: 3
Classifier: License :: OSI Approved :: BSD License
Classifier: Operating System :: OS Independent
Requires-Python: >=3.6
License-File: LICENSE
Requires-Dist: requests
